tmctl/__init__.py
tmctl/controller.py
tmctl/tmctl.py
tmctl-0.4.0.dist-info/METADATA
tmctl-0.4.0.dist-info/WHEEL
tmctl-0.4.0.dist-info/entry_points.txt
tmctl-0.4.0.dist-info/top_level.txt
tmctl-0.4.0.dist-info/RECORD
